binance/__init__.py
binance/__version__.py
binance/api.py
binance/error.py
binance/cm_futures/__init__.py
binance/cm_futures/account.py
binance/cm_futures/data_stream.py
binance/cm_futures/market.py
binance/lib/__init__.py
binance/lib/authentication.py
binance/lib/utils.py
binance/um_futures/__init__.py
binance/um_futures/account.py
binance/um_futures/convert.py
binance/um_futures/data_stream.py
binance/um_futures/market.py
binance/websocket/__init__.py
binance/websocket/binance_socket_manager.py
binance/websocket/websocket_client.py
binance/websocket/cm_futures/__init__.py
binance/websocket/cm_futures/websocket_client.py
binance/websocket/um_futures/__init__.py
binance/websocket/um_futures/websocket_client.py
binance_futures_connector-4.1.0.dist-info/LICENSE.md
binance_futures_connector-4.1.0.dist-info/METADATA
binance_futures_connector-4.1.0.dist-info/WHEEL
binance_futures_connector-4.1.0.dist-info/top_level.txt
binance_futures_connector-4.1.0.dist-info/RECORD
